phope.py
phope-0.0.10.dist-info/METADATA
phope-0.0.10.dist-info/WHEEL
phope-0.0.10.dist-info/entry_points.txt
phope-0.0.10.dist-info/top_level.txt
phope-0.0.10.dist-info/RECORD
