Metadata-Version: 2.1
Name: phope
Version: 0.0.10
Summary: universal biomarker prediction tool
Home-page: https://github.com/y-takefuji/patient
Author: yoshiyasu takefuji
Author-email: takefuji@keio.jp
License: UNKNOWN
Project-URL: Bug Tracker, https://github.com/y-takefuji/patient
Platform: UNKNOWN
Classifier: Programming Language :: Python :: 3
Classifier: License :: OSI Approved :: MIT License
Classifier: Operating System :: OS Independent
Requires-Python: >=3.8
